Metadata-Version: 2.1
Name: Database-By-Charan
Version: 2
Summary: Database-By-Charan
Home-page: UNKNOWN
Author: Charan
Author-email: schv200415@gmail.com
License: MIT
Keywords: calculator
Platform: UNKNOWN
Classifier: Development Status :: 5 - Production/Stable
Classifier: Intended Audience :: Education
Classifier: Operating System :: Microsoft :: Windows :: Windows 10
Classifier: License :: OSI Approved :: MIT License
Classifier: Programming Language :: Python :: 3
License-File: LICENCE.txt
